ai_models_multio/__init__.py
ai_models_multio/_version.py
ai_models_multio/output.py
ai_models_multio/plans.py
ai_models_multio/fdb/example_config.yaml
ai_models_multio/fdb/example_schema
ai_models_multio/templates/README.md
ai_models_multio/templates/default.tmpl
ai_models_multio/templates/regular_ll_pl_grib1.tmpl
ai_models_multio/templates/regular_ll_pl_grib2.tmpl
ai_models_multio/templates/regular_ll_sfc_grib1.tmpl
ai_models_multio/templates/regular_ll_sfc_grib2.tmpl
ai_models_multio-0.0.2.dist-info/LICENSE
ai_models_multio-0.0.2.dist-info/METADATA
ai_models_multio-0.0.2.dist-info/WHEEL
ai_models_multio-0.0.2.dist-info/entry_points.txt
ai_models_multio-0.0.2.dist-info/top_level.txt
ai_models_multio-0.0.2.dist-info/RECORD
